mibody/__init__.py
mibody/processor.py
python_mibody-0.1.2.dist-info/DESCRIPTION.rst
python_mibody-0.1.2.dist-info/METADATA
python_mibody-0.1.2.dist-info/metadata.json
python_mibody-0.1.2.dist-info/RECORD
python_mibody-0.1.2.dist-info/top_level.txt
python_mibody-0.1.2.dist-info/WHEEL
