Metadata-Version: 2.0
Name: python-mibody
Version: 0.1.2
Summary: Lightweight open source Python 3 package for reading data from Salter MiBody scales
Home-page: https://github.com/danielward/python-mibody
Author: Daniel Ward
Author-email: d@d-w.me
License: UNKNOWN
Download-URL: https://github.com/danielward/python-mibody/tarball/0.1.2
Platform: UNKNOWN
Requires-Dist: docopt (==0.6.2)
